AUTHORS.rst
CONTRIBUTING.rst
HISTORY.rst
LICENSE
MANIFEST.in
README.rst
setup.cfg
setup.py
docs/Makefile
docs/authors.rst
docs/conf.py
docs/contributing.rst
docs/history.rst
docs/index.rst
docs/installation.rst
docs/make.bat
docs/readme.rst
docs/usage.rst
tests/keys.py
tests/test_account.py
tests/test_authentication.py
tests/test_certifications.py
tests/test_changes.py
tests/test_collections.py
tests/test_companies.py
tests/test_configuration.py
tests/test_credits.py
tests/test_discovers.py
tests/test_genres.py
tests/test_guest_sessions.py
tests/test_keywords.py
tests/test_lists.py
tests/test_movies.py
tests/test_networks.py
tests/test_people.py
tests/test_reviews.py
tests/test_searches.py
tests/test_trendings.py
tests/test_tvs.py
tmdb_wrapper/__init__.py
tmdb_wrapper.egg-info/PKG-INFO
tmdb_wrapper.egg-info/SOURCES.txt
tmdb_wrapper.egg-info/dependency_links.txt
tmdb_wrapper.egg-info/not-zip-safe
tmdb_wrapper.egg-info/requires.txt
tmdb_wrapper.egg-info/top_level.txt
tmdb_wrapper/data/__init__.py
tmdb_wrapper/data/account.py
tmdb_wrapper/data/authentication.py
tmdb_wrapper/data/author.py
tmdb_wrapper/data/certification.py
tmdb_wrapper/data/change.py
tmdb_wrapper/data/collection.py
tmdb_wrapper/data/company.py
tmdb_wrapper/data/configuration.py
tmdb_wrapper/data/country.py
tmdb_wrapper/data/credit.py
tmdb_wrapper/data/dates.py
tmdb_wrapper/data/detail.py
tmdb_wrapper/data/discover.py
tmdb_wrapper/data/external_id.py
tmdb_wrapper/data/genre.py
tmdb_wrapper/data/image.py
tmdb_wrapper/data/keyword.py
tmdb_wrapper/data/language.py
tmdb_wrapper/data/list.py
tmdb_wrapper/data/media.py
tmdb_wrapper/data/movie.py
tmdb_wrapper/data/network.py
tmdb_wrapper/data/now_playing.py
tmdb_wrapper/data/person.py
tmdb_wrapper/data/provider.py
tmdb_wrapper/data/release_date.py
tmdb_wrapper/data/review.py
tmdb_wrapper/data/search.py
tmdb_wrapper/data/season.py
tmdb_wrapper/data/status.py
tmdb_wrapper/data/title.py
tmdb_wrapper/data/translation.py
tmdb_wrapper/data/tv.py
tmdb_wrapper/data/video.py
tmdb_wrapper/tmdb/__init__.py
tmdb_wrapper/tmdb/account.py
tmdb_wrapper/tmdb/authentication.py
tmdb_wrapper/tmdb/base.py
tmdb_wrapper/tmdb/certifications.py
tmdb_wrapper/tmdb/changes.py
